naif_pds4_bundler-1.7.2-py3.13-nspkg.pth
naif_pds4_bundler-1.7.2.dist-info/licenses/LICENSE.txt
naif_pds4_bundler-1.7.2.dist-info/licenses/NOTICE.txt
pds/naif_pds4_bundler/VERSION.txt
pds/naif_pds4_bundler/__init__.py
pds/naif_pds4_bundler/__main__.py
pds/naif_pds4_bundler/classes/__init__.py
pds/naif_pds4_bundler/classes/bundle.py
pds/naif_pds4_bundler/classes/collection.py
pds/naif_pds4_bundler/classes/label.py
pds/naif_pds4_bundler/classes/list.py
pds/naif_pds4_bundler/classes/log.py
pds/naif_pds4_bundler/classes/object.py
pds/naif_pds4_bundler/classes/product.py
pds/naif_pds4_bundler/classes/setup.py
pds/naif_pds4_bundler/data/configuration.xsd
pds/naif_pds4_bundler/data/registered_context_products.json
pds/naif_pds4_bundler/data/insight_spice/bundle_insight_spice_v008.xml
pds/naif_pds4_bundler/data/insight_spice/readme.txt
pds/naif_pds4_bundler/data/insight_spice/document/collection_document_inventory_v002.csv
pds/naif_pds4_bundler/data/insight_spice/document/collection_document_v002.xml
pds/naif_pds4_bundler/data/insight_spice/document/spiceds_v002.html
pds/naif_pds4_bundler/data/insight_spice/document/spiceds_v002.xml
pds/naif_pds4_bundler/data/insight_spice/miscellaneous/collection_miscellaneous_inventory_v008.csv
pds/naif_pds4_bundler/data/insight_spice/miscellaneous/collection_miscellaneous_v008.xml
pds/naif_pds4_bundler/data/insight_spice/miscellaneous/checksum/checksum_v008.xml
pds/naif_pds4_bundler/data/insight_spice/spice_kernels/collection_spice_kernels_inventory_v008.csv
pds/naif_pds4_bundler/data/insight_spice/spice_kernels/collection_spice_kernels_v008.xml
pds/naif_pds4_bundler/data/insight_spice/spice_kernels/ck/insight_ida_enc_190929_191120_v1.xml
pds/naif_pds4_bundler/data/insight_spice/spice_kernels/fk/insight_v05.xml
pds/naif_pds4_bundler/data/insight_spice/spice_kernels/ik/insight_ant_v00.xml
pds/naif_pds4_bundler/data/insight_spice/spice_kernels/lsk/naif0012.xml
pds/naif_pds4_bundler/data/insight_spice/spice_kernels/mk/insight_v08.xml
pds/naif_pds4_bundler/data/insight_spice/spice_kernels/pck/pck00010.xml
naif_pds4_bundler-1.7.2.dist-info/METADATA
naif_pds4_bundler-1.7.2.dist-info/WHEEL
naif_pds4_bundler-1.7.2.dist-info/entry_points.txt
naif_pds4_bundler-1.7.2.dist-info/namespace_packages.txt
naif_pds4_bundler-1.7.2.dist-info/top_level.txt
naif_pds4_bundler-1.7.2.dist-info/RECORD
