Metadata-Version: 2.4
Name: naif-pds4-bundler
Version: 1.7.2
Summary: NAIF PDS4 Bundler (naif-pds4-bundler) is a software package that generates a PDS4 SPICE archives.
Home-page: https://github.com/NASA-PDS/naif-pds4-bundler
Download-URL: https://github.com/NASA-PDS/naif-pds4-bundler/releases/
Author: Marc Costa Sitja, Alyssa M Bailey (NAIF/JPL)
Author-email: alyssa.m.bailey@jpl.nasa.gov
License: apache-2.0
Keywords: pds,planetary data,various,other,keywords
Classifier: Programming Language :: Python :: 3
Classifier: Programming Language :: Python :: 3.8
Classifier: License :: OSI Approved :: Apache Software License
Classifier: Operating System :: Unix
Requires-Python: >=3.8
License-File: LICENSE.txt
License-File: NOTICE.txt
Requires-Dist: spiceypy>=4.0.2
Requires-Dist: beautifulsoup4>=4.9.3
Requires-Dist: setuptools>=50.3.0
Requires-Dist: nose
Requires-Dist: coverage
Requires-Dist: xmlschema
Requires-Dist: requests
Provides-Extra: dev
Requires-Dist: pep8-naming; extra == "dev"
Requires-Dist: mypy; extra == "dev"
Requires-Dist: pydocstyle; extra == "dev"
Requires-Dist: coverage; extra == "dev"
Requires-Dist: pytest; extra == "dev"
Requires-Dist: pytest-cov; extra == "dev"
Requires-Dist: pytest-watch; extra == "dev"
Requires-Dist: pytest-xdist; extra == "dev"
Requires-Dist: pre-commit; extra == "dev"
Requires-Dist: sphinx; extra == "dev"
Requires-Dist: sphinx-rtd-theme; extra == "dev"
Requires-Dist: tox; extra == "dev"
Requires-Dist: types-setuptools; extra == "dev"
Dynamic: download-url
Dynamic: license-file
